eunicore/__init__.py
eunicore/apps.py
eunicore/auth_hooks.py
eunicore/urls.py
eunicore/views.py
eunicore/auth/__init__.py
eunicore/auth/backends.py
eunicore/management/commands/eunicore_force_nightmode.py
eunicore/static/eunicore/css/main.css
eunicore/static/eunicore/css/main.min.css
eunicore/static/eunicore/css/main.min.css.map
eunicore/static/eunicore/fonts/bootstrap/glyphicons-halflings-regular.eot
eunicore/static/eunicore/fonts/bootstrap/glyphicons-halflings-regular.svg
eunicore/static/eunicore/fonts/bootstrap/glyphicons-halflings-regular.ttf
eunicore/static/eunicore/fonts/bootstrap/glyphicons-halflings-regular.woff
eunicore/static/eunicore/fonts/bootstrap/glyphicons-halflings-regular.woff2
eunicore/static/eunicore/icons/allianceauth.png
eunicore/static/eunicore/icons/apple-touch-icon.png
eunicore/static/eunicore/icons/favicon-16x16.png
eunicore/static/eunicore/icons/favicon-32x32.png
eunicore/static/eunicore/icons/favicon-96x96.png
eunicore/static/eunicore/icons/favicon.ico
eunicore/static/eunicore/scss/_callout.scss
eunicore/static/eunicore/scss/_gen_banner.scss
eunicore/static/eunicore/scss/_variables.scss
eunicore/static/eunicore/scss/main.scss
eunicore/template/__init__.py
eunicore/template/backends.py
eunicore/templates/allianceauth/base.html
eunicore/templates/allianceauth/icons.html
eunicore/templates/allianceauth/top-menu-user-dropdown.html
eunicore/templates/bundles/euni-css.html
eunicore/tests/__init__.py
eunicore/tests/test_auth.py
eunicore/tests/test_command.py
eunicore/theme/__init__.py
eunicore/theme/slate/__init__.py
eunicore/theme/slate/apps.py
eunicore/theme/slate/auth_hooks.py
eunicore/theme/slate/static/eunicore/theme/slate/css/tweaks.css
aa_euni_core-0.1.1.dist-info/LICENSE
aa_euni_core-0.1.1.dist-info/METADATA
aa_euni_core-0.1.1.dist-info/WHEEL
aa_euni_core-0.1.1.dist-info/top_level.txt
aa_euni_core-0.1.1.dist-info/RECORD
