Metadata-Version: 2.1
Name: aa_euni_core
Version: 0.1.1
Summary: EVE University Core Plugin for Alliance Auth
Home-page: https://github.com/EVE-University/aa-euni-core
Author: Marn Vermuldir
Author-email: marn@minin.io
Maintainer: Marn Vermuldir
Maintainer-email: marn@minin.io
License: MIT
Project-URL: Issue / Bug Reports, https://github.com/EVE-University/aa-euni-core/issues
Project-URL: Changelog, https://github.com/EVE-University/aa-euni-core/blob/master/CHANGELOG.md
Keywords: allianceauth,eunicore
Classifier: Environment :: Web Environment
Classifier: Framework :: Django
Classifier: Framework :: Django :: 4.0
Classifier: Intended Audience :: Developers
Classifier: License :: OSI Approved :: MIT License
Classifier: Operating System :: OS Independent
Classifier: Programming Language :: Python
Classifier: Programming Language :: Python :: 3
Classifier: Programming Language :: Python :: 3.8
Classifier: Programming Language :: Python :: 3.9
Classifier: Programming Language :: Python :: 3.10
Classifier: Topic :: Internet :: WWW/HTTP
Classifier: Topic :: Internet :: WWW/HTTP :: Dynamic Content
Requires-Python: ~=3.8
License-File: LICENSE
Requires-Dist: allianceauth>=3.0.0
